muffin_kafka/__init__.py
muffin_kafka/plugin.py
muffin_kafka/py.typed
muffin_kafka-0.9.3.dist-info/METADATA
muffin_kafka-0.9.3.dist-info/WHEEL
muffin_kafka-0.9.3.dist-info/RECORD
