Metadata-Version: 2.3
Name: muffin-kafka
Version: 0.9.3
Summary: Kafka Integration for Muffin framework
License: MIT
Keywords: kafka,asyncio,asgi,muffin
Author: Kirill Klenov
Author-email: horneds@gmail.com
Requires-Python: >=3.10,<4.0
Classifier: Development Status :: 5 - Production/Stable
Classifier: Framework :: AsyncIO
Classifier: Intended Audience :: Developers
Classifier: License :: OSI Approved :: MIT License
Classifier: Programming Language :: Python
Classifier: Programming Language :: Python :: 3
Classifier: Programming Language :: Python :: 3.10
Classifier: Programming Language :: Python :: 3.11
Classifier: Programming Language :: Python :: 3.12
Classifier: Programming Language :: Python :: 3.13
Classifier: Topic :: Internet :: WWW/HTTP
Requires-Dist: aiokafka[lz4]
Requires-Dist: muffin
Project-URL: Homepage, https://github.com/klen/muffin-kafka
Project-URL: Repository, https://github.com/klen/muffin-kafka
